LICENSE
MANIFEST.in
README.md
requirements.txt
setup.py
lelesk/__init__.py
lelesk/__main__.py
lelesk/__version__.py
lelesk/config.py
lelesk/main.py
lelesk/util.py
lelesk/wsdtk.py
lelesk.egg-info/PKG-INFO
lelesk.egg-info/SOURCES.txt
lelesk.egg-info/dependency_links.txt
lelesk.egg-info/requires.txt
lelesk.egg-info/top_level.txt
lelesk/script/lesk_cache.sql
test/test_lelesk.py
test/test_util.py