Metadata-Version: 2.1
Name: lelesk
Version: 0.1
Summary: A fast Python implementation of the extended LESK algorithm for Word-Sense Disambiguation (WSD)
Home-page: https://github.com/letuananh/lelesk
Author: Le Tuan Anh
Author-email: tuananh.ke@gmail.com
License: MIT License
Project-URL: Bug Tracker, https://github.com/letuananh/lelesk/issues
Project-URL: Source Code, https://github.com/letuananh/lelesk/
Keywords: wsd,word-sense disambiguation,word,sense,disambiguation,semantics,nlp,text
Platform: any
Classifier: Programming Language :: Python
Classifier: Development Status :: 5 - Production/Stable
Classifier: License :: OSI Approved :: MIT License
Classifier: Environment :: Plugins
Classifier: Intended Audience :: Education
Classifier: Intended Audience :: Science/Research
Classifier: Intended Audience :: Information Technology
Classifier: Intended Audience :: Developers
Classifier: Operating System :: OS Independent
Classifier: Topic :: Text Processing
Classifier: Topic :: Text Processing :: Linguistic
Classifier: Topic :: Software Development :: Libraries :: Python Modules
Requires-Python: >=3.6
